scelda/models.py
scelda/nets.py
scelda/sim.py
scelda/util.py
scelda-0.0.5.dist-info/METADATA
scelda-0.0.5.dist-info/WHEEL
scelda-0.0.5.dist-info/top_level.txt
scelda-0.0.5.dist-info/RECORD
