Metadata-Version: 2.1
Name: scelda
Version: 0.0.5
Project-URL: Homepage, https://github.com/Computational-Morphogenomics-Group/sceLDA
Requires-Dist: numpy
Requires-Dist: tqdm
Requires-Dist: torch
Requires-Dist: matplotlib
Requires-Dist: muon
Requires-Dist: pyro-ppl
Provides-Extra: test
Requires-Dist: pytest ; extra == 'test'
Requires-Dist: pytest-cov ; extra == 'test'
